xkcd_random/__about__.py
xkcd_random/__init__.py
xkcd_random/_random.py
xkcd_random/override_style.py
xkcd_random/py.typed
xkcd_random_four-0.1.1.dist-info/METADATA
xkcd_random_four-0.1.1.dist-info/WHEEL
xkcd_random_four-0.1.1.dist-info/entry_points.txt
xkcd_random_four-0.1.1.dist-info/licenses/LICENSE
xkcd_random_four-0.1.1.dist-info/RECORD
