Metadata-Version: 2.4
Name: xkcd-random-four
Version: 0.1.1
Summary: Drop in replacment for random that always returns 4 or 4/6
Project-URL: Homepage, https://github.com/matthewdeanmartin/xkcd-random
Project-URL: Bug Tracker, https://github.com/matthewdeanmartin/xkcd-random/issues
Author-email: Matthew Dean Martin <matthewdeanmartin@gmail.com>
License-File: LICENSE
Classifier: Development Status :: 1 - Planning
Classifier: License :: OSI Approved :: MIT License
Classifier: Operating System :: OS Independent
Classifier: Programming Language :: Python
Classifier: Programming Language :: Python :: 3
Classifier: Programming Language :: Python :: 3.8
Classifier: Programming Language :: Python :: 3.9
Classifier: Programming Language :: Python :: 3.10
Classifier: Programming Language :: Python :: 3.11
Classifier: Programming Language :: Python :: 3.12
Classifier: Programming Language :: Python :: 3.13
Classifier: Programming Language :: Python :: 3.14
Classifier: Programming Language :: Python :: 3.15
Classifier: Topic :: Software Development :: Libraries :: Python Modules
Requires-Python: >=3.8
